tavo/__init__.py
tavo/client.py
tavo_sdk-0.4.0.dist-info/METADATA
tavo_sdk-0.4.0.dist-info/WHEEL
tavo_sdk-0.4.0.dist-info/top_level.txt
tavo_sdk-0.4.0.dist-info/RECORD
